RsSmw
